Talnakh/SqlServerSeeder/__init__.py
Talnakh/SqlServerSeeder/py.typed
Talnakh/SqlServerSeeder/_jsii/__init__.py
Talnakh/SqlServerSeeder/_jsii/cdk-sqlserver-seeder@0.2.3.jsii.tgz
cdk_sqlserver_seeder-0.2.3.dist-info/METADATA
cdk_sqlserver_seeder-0.2.3.dist-info/WHEEL
cdk_sqlserver_seeder-0.2.3.dist-info/top_level.txt
cdk_sqlserver_seeder-0.2.3.dist-info/RECORD
