Metadata-Version: 2.1
Name: cdk-sqlserver-seeder
Version: 0.2.3
Summary: A simple CDK seeder for SQL Server RDS databases.
Home-page: https://github.com/kolomied/cdk-sqlserver-seeder#readme
Author: Dmitry Kolomiets<kolomied@amazon.co.uk>
License: MIT
Project-URL: Source, https://github.com/kolomied/cdk-sqlserver-seeder.git
Platform: UNKNOWN
Classifier: Intended Audience :: Developers
Classifier: Operating System :: OS Independent
Classifier: Programming Language :: JavaScript
Classifier: Programming Language :: Python :: 3 :: Only
Classifier: Programming Language :: Python :: 3.6
Classifier: Programming Language :: Python :: 3.7
Classifier: Programming Language :: Python :: 3.8
Classifier: Typing :: Typed
Classifier: Development Status :: 4 - Beta
Classifier: License :: OSI Approved
Requires-Python: >=3.6
Requires-Dist: jsii (<2.0.0,>=1.8.0)
Requires-Dist: publication (>=0.0.3)
Requires-Dist: aws-cdk.aws-lambda (<2.0.0,>=1.49.1)
Requires-Dist: aws-cdk.aws-rds (<2.0.0,>=1.49.1)
Requires-Dist: aws-cdk.aws-s3 (<2.0.0,>=1.49.1)
Requires-Dist: aws-cdk.aws-s3-deployment (<2.0.0,>=1.49.1)
Requires-Dist: aws-cdk.aws-secretsmanager (<2.0.0,>=1.49.1)
Requires-Dist: aws-cdk.core (<2.0.0,>=1.49.1)
Requires-Dist: aws-cdk.custom-resources (<2.0.0,>=1.49.1)
Requires-Dist: constructs (<4.0.0,>=3.0.4)
